{
  "id": "ax-02",
  "name": "Heron",
  "_doc": "Endurance ISR airframe (docs/03): low ceiling, slow, deliberate approvals. Forces profile-reading (its 50 m/s ceiling rejects a brain that hardcoded AX-01's Speed:60) and exercises the PENDING->APPROVED control flow (approvalLatencyTicks 3).",
  "capabilities": [
    {
      "id": "CAP-HSA",
      "type": "HSA_CSA",
      "profile": {
        "minAltitude": 0,
        "maxAltitude": 8000,
        "minAirspeed": 25,
        "maxAirspeed": 50
      }
    }
  ],
  "flight": {
    "maxTurnRateDeg": 3,
    "maxClimbRate": 30,
    "maxAccel": 10
  },
  "control": {
    "approvalLatencyTicks": 3
  },
  "publish": {
    "positionIntervalTicks": 1,
    "activityIntervalTicks": 5
  },
  "start": {
    "x": 0,
    "y": 0,
    "altitude": 3000,
    "heading": 270,
    "speed": 35
  }
}
